timeless/__init__.py
timeless/converters/__init__.py
timeless/converters/datetime_converter.py
timeless/converters/numpy_converter.py
timeless/converters/pandas_converter.py
timeless/datetime.py
timeless/helpers.py
timeless/period.py
timeless/py.typed
timeless-0.2.7.dist-info/WHEEL
timeless-0.2.7.dist-info/METADATA
timeless-0.2.7.dist-info/RECORD
