Metadata-Version: 2.1
Name: timeless
Version: 0.2.7
Summary: Datetime for people in a hurry.
Home-page: https://github.com/ericmiguel/timeless
License: MIT
Keywords: datetime,datetime for humans
Author: ericmiguel
Author-email: ericmiguel@id.uff.br
Requires-Python: >=3.8,<4.0
Classifier: License :: OSI Approved :: MIT License
Classifier: Programming Language :: Python :: 3
Classifier: Programming Language :: Python :: 3.8
Classifier: Programming Language :: Python :: 3.9
Classifier: Programming Language :: Python :: 3.10
Classifier: Programming Language :: Python :: 3.11
Provides-Extra: converters
Requires-Dist: backports-zoneinfo (>=0.2.1,<0.3.0); python_version < "3.9"
Requires-Dist: pandas (>=1.5.1,<2.0.0); extra == "converters"
Requires-Dist: python-dateutil (>=2.8.2,<3.0.0)
Requires-Dist: typing-extensions (>=4.4.0,<5.0.0)
Requires-Dist: tzdata (>=2022.6,<2023.0); sys_platform == "win32"
Project-URL: Repository, https://github.com/ericmiguel/timeless
